[
    {
        "number": 1,
        "type": "말조련사사",
        "subject": "마학",
        "question": "다음 중 말의 진화 방향으로 옳은 것은?",
        "choices": ["에오히푸스-메소히푸스-에쿠스-플리오히푸스-에릭히푸스", "에오히푸스-메릭히푸스-메소히푸스-에쿠스-플리오히푸스", "에오히푸스-메소히푸스-메릭히푸스-플리오히푸스-에쿠스", "에쿠스-플리오히푸스-메릭히푸스-메소히푸스-에오히푸스"],
        "answer": 2,
        "explanation": "답은 3번으로 에오히푸스에서 메소히푸스, 메릭히푸스, 플리오히푸스, 에쿠스 순서로 진화했다."
    },
    {
        "number": 2,
        "type": "말조련사사",
        "subject": "마학",
        "question": "말의 최초의 선조로 보고 있는 이 말의 이름은?",
        "choices": ["에오히푸스", "메릭히푸스", "에쿠스", "플리오히푸스"],
        "answer": 0,
        "explanation": "답은 1번으로 가장 오래된 말과 유사한 화석은 신생대 (약 5,000만 년 전) 지층에서 발견되었는데 이것을 말의 최초 선조로 보고 있으며 '에오히푸스' 라고 한다"
    },
    {
        "number": 3,
        "type": "말조련사사",
        "subject": "마학",
        "question": "발가락이 하나인 말의 말의 조상이다. 체고는 약 110~ 120cm 정도였도. 둘째와 넷째 발가락은 거의 사라져 흔적만 남아 있어서",
        "choices": ["에오히푸스", "메릭히푸스", "에쿠스", "플리오히푸스"],
        "answer": 0,
        "explanation": "답은 1번으로 가장 오래된 말과 유사한 화석은 신생대 (약 5,000만 년 전) 지층에서 발견되었는데 이것을 말의 최초 선조로 보고 있으며 '에오히푸스' 라고 한다"
    },
]